[
  {
    "id": "sandbox_training",
    "name": "训练场",
    "description": "是的，这里是PVP！找你的朋友要个卡组代码吧！",
    "unlockRequirementId": null,
    "teamSize": 1,
    "unlocksPackId": null,
    "goldRewardMin": 0,
    "goldRewardMax": 0,
    "stages": [
      { "type": "mob", "enemyPoolId": "training_mob" }
    ]
  },
  {
    "id": "training_ground",
    "name": "初心剑馆",
    "description": "新手的试炼之地。",
    "unlockRequirementId": null,
    "teamSize": 1,
    "unlocksPackId": "basic_swordsmanship",
    "goldRewardMin": 10,
    "goldRewardMax": 10,
    "stages": [
      { "type": "mob", "enemyPoolId": "training_mob" },
      { "type": "mob", "enemyPoolId": "training_mob" },
      { "type": "elite", "enemyPoolId": "training_elite" },
      { "type": "mob", "enemyPoolId": "training_mob" },
      { "type": "mob", "enemyPoolId": "training_mob" },
      { "type": "boss", "enemyPoolId": "training_boss" }
    ]
  },
  {
    "id": "magic_academy_visitor",
    "name": "魔法学院来客",
    "description": "来自远方魔法学院的访问者。",
    "unlockRequirementId": "training_ground",
    "teamSize": 1,
    "unlocksPackId": "sword_and_magic",
    "goldRewardMin": 20,
    "goldRewardMax": 20,
    "stages": [
      { "type": "mob", "enemyPoolId": "magic_mob" },
      { "type": "mob", "enemyPoolId": "magic_mob" },
      { "type": "elite", "enemyPoolId": "magic_elite" },
      { "type": "mob", "enemyPoolId": "magic_mob" },
      { "type": "mob", "enemyPoolId": "magic_mob" },
      { "type": "elite", "enemyPoolId": "magic_elite" },
      { "type": "mob", "enemyPoolId": "magic_mob" },
      { "type": "mob", "enemyPoolId": "magic_mob" },
      { "type": "elite", "enemyPoolId": "magic_elite" }
    ]
  },
  {
    "id": "fiery_duelist",
    "name": "热烈的决斗者",
    "description": "也算一种打牌",
    "unlockRequirementId": "training_ground",
    "teamSize": 1,
    "unlocksPackId": "pack_3_lakshir_ritual",
    "goldRewardMin": 1,
    "goldRewardMax": 1,
    "stages": [
      { "type": "boss", "enemyPoolId": "fiery_duelist_boss" }
    ]
  },
  {
    "id": "variable_gear_start",
    "name": "变速齿轮，启动！",
    "description": "（正在开着鼠标连点器挂机…）",
    "designer": "木头",
    "unlockRequirementId": "training_ground",
    "teamSize": 1,
    "unlocksPackId": "pack_4_variable_gear",
    "goldRewardMin": 10,
    "goldRewardMax": 10,
    "stages": [
      { "type": "mob", "enemyPoolId": "variable_gear_mob" },
      { "type": "mob", "enemyPoolId": "variable_gear_mob" },
      { "type": "mob", "enemyPoolId": "variable_gear_mob" },
      { "type": "mob", "enemyPoolId": "variable_gear_mob" },
      { "type": "mob", "enemyPoolId": "variable_gear_mob" },
      { "type": "mob", "enemyPoolId": "variable_gear_mob" },
      { "type": "boss", "enemyPoolId": "variable_gear_boss" }
    ]
  },
  {
    "id": "dung_poop_zone",
    "name": "粪怪地带",
    "description": "冒险者还不知道马上他要面对什么……",
    "designer": "橘猫",
    "unlockRequirementId": "training_ground",
    "teamSize": 1,
    "unlocksPackId": "pack_5_trick_of_god",
    "goldRewardMin": 20,
    "goldRewardMax": 20,
    "stages": [
      { "type": "mob", "enemyPoolId": "poop_zone_mob" },
      { "type": "mob", "enemyPoolId": "poop_zone_mob" },
      { "type": "elite", "enemyPoolId": "poop_zone_elite" },
      { "type": "mob", "enemyPoolId": "poop_zone_mob" },
      { "type": "mob", "enemyPoolId": "poop_zone_mob" },
      { "type": "elite", "enemyPoolId": "poop_zone_elite" }
    ]
  }
]
